task1/lfsr.sv
module lfsr4 (
    input logic clk,    // clock
    input logic rst,    // reset
    input logic en,      // enable signal
    output logic [6:0] data_out // pseudo-random output
);

logic [6:0] sreg;

always_ff @(posedge clk, posedge rst)
    if (rst)
        sreg <= 7'b1;
    else 
        sreg <= {sreg[5:0], sreg[2] ^ sreg[6]};

assign data_out = sreg;

endmodule

// module lfsr(
//     input logic clk,
//     input logic rst,
//     input logic en,
//     output logic [3:0] data_out
// );

//     logic [3:0] sreg;
//     logic sreg3_xor_sreg4;

//     assign sreg3_xor_sreg4 = sreg[2] ^ sreg[3];

//     always_ff @(posedge clk) begin
//         if (rst) begin
//             sreg <= 4'b0001;
//         end else if (en) begin
//             sreg <= {sreg[2:0], sreg3_xor_sreg4};
//         end
//     end

//     assign data_out = sreg;

// endmodule

task1/lfsr.vcd
$version Generated by VerilatedVcd $end
$timescale 1ps $end

 $scope module TOP $end
  $var wire  1 # clk $end
  $var wire  7 & data_out [6:0] $end
  $var wire  1 % en $end
  $var wire  1 $ rst $end
  $scope module lfsr4 $end
   $var wire  1 # clk $end
   $var wire  7 & data_out [6:0] $end
   $var wire  1 % en $end
   $var wire  1 $ rst $end
   $var wire  7 ' sreg [6:0] $end
  $upscope $end
 $upscope $end
$enddefinitions $end


#0
1#
1$
0%
b0000000 &
b0000000 '
#1
0#
#2
1#
b0000001 &
b0000001 '
#3
0#
#4
1#
0$
#5
0#
#6
1#
b0000010 &
b0000010 '
#7
0#
#8
1#
b0000100 &
b0000100 '
#9
0#
#10
1#
b0001001 &
b0001001 '
#11
0#
#12
1#
b0010010 &
b0010010 '
#13
0#
#14
1#
b0100100 &
b0100100 '
#15
0#
#16
1#
b1001001 &
b1001001 '
#17
0#
#18
1#
b0010011 &
b0010011 '
#19
0#
#20
1#
b0100110 &
b0100110 '
#21
0#
#22
1#
b1001101 &
b1001101 '
#23
0#
#24
1#
b0011010 &
b0011010 '
#25
0#
#26
1#
b0110100 &
b0110100 '
#27
0#
#28
1#
b1101001 &
b1101001 '
#29
0#
#30
1#
b1010011 &
b1010011 '
#31
0#
#32
1#
b0100111 &
b0100111 '
#33
0#
#34
1#
b1001111 &
b1001111 '
#35
0#
#36
1#
b0011110 &
b0011110 '
#37
0#
#38
1#
b0111101 &
b0111101 '
